urlconfirm/__init__.py
urlconfirm/urlconfirm.py
urlconfirm-2.0.dist-info/LICENSE.txt
urlconfirm-2.0.dist-info/METADATA
urlconfirm-2.0.dist-info/WHEEL
urlconfirm-2.0.dist-info/top_level.txt
urlconfirm-2.0.dist-info/RECORD
