Metadata-Version: 2.1
Name: urlconfirm
Version: 2.0
Summary: Check whether the user's data is a URL.
Home-page: https://www.kwserver.store
Author: Allen_Lee
Author-email: paranelf66@gmail.com
Project-URL: Bug Tracker, https://www.kwserver.store
Classifier: Programming Language :: Python :: 3
Classifier: License :: OSI Approved :: MIT License
Classifier: Operating System :: OS Independent
Requires-Python: >=3.10
License-File: LICENSE.txt
